dasi/__init__.py
dasi/__version__.py
dasi/command_line/__init__.py
dasi/config.py
dasi/constants.py
dasi/cost/__init__.py
dasi/cost/cached_span_cost.py
dasi/cost/default_parameters.json
dasi/cost/span_cost.checksum
dasi/cost/span_cost.py
dasi/cost/utils.py
dasi/design/__init__.py
dasi/design/design.py
dasi/design/design_result.py
dasi/design/designabc.py
dasi/design/graph_builder.py
dasi/design/library_design.py
dasi/design/optimize.py
dasi/design/output.py
dasi/design/report.py
dasi/exceptions.py
dasi/log.py
dasi/models/__init__.py
dasi/models/alignment.py
dasi/models/alignment_container.py
dasi/models/assembly.py
dasi/models/molecule.py
dasi/schemas/__init__.py
dasi/schemas/output_schema.json
dasi/schemas/parameter_json_schema.json
dasi/utils/__init__.py
dasi/utils/biopython/__init__.py
dasi/utils/biopython/record_to_json.py
dasi/utils/biopython/sequence.py
dasi/utils/networkx/__init__.py
dasi/utils/networkx/algorithms.py
dasi/utils/networkx/exceptions.py
dasi/utils/networkx/shortest_path.py
dasi/utils/networkx/utils.py
dasi/utils/npdf.py
dasi/utils/region.py
dasi/utils/sequence/__init__.py
dasi/utils/sequence/sequence_complexity.py
dasi/utils/sequence/sequence_generator.py
dasi/utils/sequence/sequence_partitioner.py
dasi/utils/testing_utils.py
dasi-0.2.1.dist-info/entry_points.txt
dasi-0.2.1.dist-info/LICENSE
dasi-0.2.1.dist-info/WHEEL
dasi-0.2.1.dist-info/METADATA
dasi-0.2.1.dist-info/RECORD
