Metadata-Version: 2.1
Name: dasi
Version: 0.2.1
Summary: Automated DNA assembly planner for Python
Home-page: https://github.com/jvrana/dasi-dna-design
Author: Justin Vrana
Author-email: justin.vrana@gmail.com
Requires-Python: >=3.6.1,<4.0.0
Classifier: Development Status :: 4 - Beta
Classifier: Intended Audience :: Science/Research
Classifier: Programming Language :: Python :: 3
Classifier: Programming Language :: Python :: 3.7
Classifier: Programming Language :: Python :: 3.8
Classifier: Programming Language :: Python :: 3.9
Classifier: Topic :: Scientific/Engineering :: Bio-Informatics
Provides-Extra: documentation
Provides-Extra: styling
Requires-Dist: autodocsumm (>=0.1.11,<0.2.0)
Requires-Dist: biopython (>=1.78,<2.0)
Requires-Dist: black (>=20.8b1,<21.0); extra == "styling"
Requires-Dist: flake8 (>=3.7,<4.0); extra == "styling"
Requires-Dist: frozendict (>=1.2,<2.0)
Requires-Dist: jdna (>=0.2,<0.3)
Requires-Dist: jsonschema (>=3.1,<4.0)
Requires-Dist: loggable-jdv (>=0.1.5,<0.2.0)
Requires-Dist: matplotlib (>=3.1,<4.0)
Requires-Dist: more-itertools (>=8.0,<9.0)
Requires-Dist: msgpack (>=0.6.1,<0.7.0)
Requires-Dist: msgpack-numpy (>=0.4.4,<0.5.0)
Requires-Dist: nbsphinx (>=0.4.2,<0.5.0); extra == "documentation"
Requires-Dist: networkx (>=2.3,<3.0)
Requires-Dist: numpy (>=1.17,<2.0)
Requires-Dist: pandas (>=1.1.0,<2.0.0); python_version >= "3.7" and python_version < "4.0"
Requires-Dist: pre-commit (>=1.17,<2.0); extra == "styling"
Requires-Dist: primer3plus (>=1.0.8,<2.0.0)
Requires-Dist: pyblastbio (>=0.9,<0.10)
Requires-Dist: recommonmark (>=0.6.0,<0.7.0)
Requires-Dist: sphinx (>=2.2,<3.0); extra == "documentation"
Requires-Dist: sphinx-bootstrap-theme (>=0.7.1,<0.8.0); extra == "documentation"
Requires-Dist: sphinx-jsonschema (>=1.11,<2.0); extra == "documentation"
Requires-Dist: sphinx_autodoc_typehints (>=1.8,<2.0); extra == "documentation"
Requires-Dist: sympy (>=1.4,<2.0)
Requires-Dist: tqdm (>=4.32,<5.0)
Project-URL: Documentation, https://jvrana.github.io/dasi-dna-design
